ShamirDecode/__init__.py
ShamirDecoder-1.0.1.dist-info/METADATA
ShamirDecoder-1.0.1.dist-info/WHEEL
ShamirDecoder-1.0.1.dist-info/top_level.txt
ShamirDecoder-1.0.1.dist-info/RECORD
